lofarnn/__init__.py
lofarnn/data/__init__.py
lofarnn/data/cutouts.py
lofarnn/data/datasets.py
lofarnn/models/__init__.py
lofarnn/models/autokeras_cnn.py
lofarnn/models/cnn_optuna.py
lofarnn/models/dist_cnn.py
lofarnn/models/dist_optuna.py
lofarnn/models/radio_segmenter.py
lofarnn/models/run_baseline.py
lofarnn/models/source_finder.py
lofarnn/models/source_png.py
lofarnn/models/source_tester.py
lofarnn/models/train_cnn.py
lofarnn/models/train_net.py
lofarnn/models/base/__init__.py
lofarnn/models/base/antialiased.py
lofarnn/models/base/baselines.py
lofarnn/models/base/cnn.py
lofarnn/models/base/resnet.py
lofarnn/models/base/utils.py
lofarnn/models/dataloaders/SourceMapper.py
lofarnn/models/dataloaders/__init__.py
lofarnn/models/dataloaders/datasets.py
lofarnn/models/dataloaders/utils.py
lofarnn/models/evaluators/LossEvalHook.py
lofarnn/models/evaluators/SourceEvaluator.py
lofarnn/models/evaluators/__init__.py
lofarnn/models/trainer/SourceTrainer.py
lofarnn/models/trainer/__init__.py
lofarnn/tests/__init__.py
lofarnn/utils/__init__.py
lofarnn/utils/coco.py
lofarnn/utils/fits.py
lofarnn/visualization/__init__.py
lofarnn/visualization/cutouts.py
lofarnn/visualization/metrics.py
lofarnn/visualization/models.py
lofarnn-0.7.1.dist-info/LICENSE
lofarnn-0.7.1.dist-info/METADATA
lofarnn-0.7.1.dist-info/WHEEL
lofarnn-0.7.1.dist-info/top_level.txt
lofarnn-0.7.1.dist-info/RECORD
