Metadata-Version: 2.1
Name: lofarnn
Version: 0.7.1
Summary: UNKNOWN
Home-page: https://github.com/jacobbieker/lofarnn
Author: Jacob Bieker
Author-email: UNKNOWN
License: GPLv3
Download-URL: https://github.com/jacobbieker/lofarnn/archive/v0.7.1.tar.gz
Keywords: Radio Astronomy,PyTorch,Machine Learning
Platform: UNKNOWN
Classifier: Development Status :: 3 - Alpha
Classifier: Intended Audience :: Developers
Classifier: Topic :: Scientific/Engineering :: Astronomy
Classifier: License :: OSI Approved :: GNU General Public License v3 (GPLv3)
Classifier: Programming Language :: Python :: 3
Requires-Dist: astropy
Requires-Dist: numpy
Requires-Dist: scikit-image
Requires-Dist: pillow
Requires-Dist: pytorch
Requires-Dist: scipy
Requires-Dist: matplotlib
